MANIFEST.in
README.rst
requirements.txt
setup.py
githubmirror/__init__.py
githubmirror/main.py
githubmirror.egg-info/PKG-INFO
githubmirror.egg-info/SOURCES.txt
githubmirror.egg-info/dependency_links.txt
githubmirror.egg-info/entry_points.txt
githubmirror.egg-info/requires.txt
githubmirror.egg-info/top_level.txt