Metadata-Version: 1.0
Name: githubmirror
Version: 0.3.1
Summary: A small script to keep a copy of every repo in a Github org.
Home-page: http://github.com/martinmelin/githubmirror
Author: Martin Melin
Author-email: martin@tictail.com
License: Creative Commons Attribution-Noncommercial-Share Alike license
Platform: UNKNOWN
